cosmology/__init__.py
cosmology/_structure.py
cosmology/astropy.py
cosmology/background.py
cosmology/camb.py
cosmology-2022.10.9.dist-info/LICENSE.txt
cosmology-2022.10.9.dist-info/METADATA
cosmology-2022.10.9.dist-info/WHEEL
cosmology-2022.10.9.dist-info/top_level.txt
cosmology-2022.10.9.dist-info/RECORD
